shipyard_redshift/__init__.py
shipyard_redshift/cli/authtest.py
shipyard_redshift/cli/download.py
shipyard_redshift/cli/execute_query.py
shipyard_redshift/cli/upload.py
shipyard_redshift/redshift.py
shipyard_redshift-0.2.0.dist-info/METADATA
shipyard_redshift-0.2.0.dist-info/WHEEL
shipyard_redshift-0.2.0.dist-info/RECORD
